LICENSE
README.md
setup.py
dxh_libraries/__init__.py
dxh_libraries/__version__.py
dxh_libraries/allauth.py
dxh_libraries/celery.py
dxh_libraries/channels.py
dxh_libraries/dj_rest_auth.py
dxh_libraries/django_quill.py
dxh_libraries/drf_yasg.py
dxh_libraries/easy_thumbnails.py
dxh_libraries/easyaudit.py
dxh_libraries/fcm_django.py
dxh_libraries/import_export.py
dxh_libraries/openai.py
dxh_libraries/pywebpush.py
dxh_libraries/rest_framework.py
dxh_libraries/rest_framework_api_key.py
dxh_libraries/rest_framework_simplejwt.py
dxh_libraries/stripe.py
dxh_libraries/translation.py
dxh_libraries/twilio.py
dxh_libraries/unfold.py
dxh_libraries.egg-info/PKG-INFO
dxh_libraries.egg-info/SOURCES.txt
dxh_libraries.egg-info/dependency_links.txt
dxh_libraries.egg-info/top_level.txt